README.md
publish.py
setup.py
decapt/__init__.py
decapt/main.py
decapt/sudobg.py
decapt.egg-info/PKG-INFO
decapt.egg-info/SOURCES.txt
decapt.egg-info/dependency_links.txt
decapt.egg-info/entry_points.txt
decapt.egg-info/requires.txt
decapt.egg-info/top_level.txt