Metadata-Version: 2.1
Name: decapt
Version: 0.0.21
Summary: Arch Linux declarative package management
Home-page: https://gitlab.com/rendaw/decapt
Author: rendaw
License: MIT
Download-URL: https://gitlab.com/rendaw/decapt/-/archive/v0.0.21/decapt-v0.0.21.tar.gz
Platform: UNKNOWN
